dsar/__init__.py
dsar/core.py
dsar/frequency_bands.py
dsar/plot.py
dsar/utilities.py
dsar-1.1.0.dist-info/LICENSE
dsar-1.1.0.dist-info/WHEEL
dsar-1.1.0.dist-info/METADATA
dsar-1.1.0.dist-info/RECORD
