Metadata-Version: 2.3
Name: dsar
Version: 1.1.0
Summary: Calculating Displacement Seismic Amplitude Ratio (DSAR) Value
Keywords: seismic,volcano,volcanology,dsar
Author-email: Martanto <martanto@live.com>, Corentin Caudron <corentin@ulb.be>
Requires-Python: >=3.11
Classifier: License :: OSI Approved :: MIT License
Classifier: Operating System :: OS Independent
Classifier: Programming Language :: Python :: 3.11
Classifier: Programming Language :: Python :: 3.12
Requires-Dist: obspy>=1.4.0
Requires-Dist: openpyxl>=3.1.5
Requires-Dist: pandas>=2.2.0
Requires-Dist: magma-converter>=1.8.6
Requires-Dist: numpy>=2.0.0
Requires-Dist: matplotlib>=3.9.0
Requires-Dist: peewee>=3.17.6
Requires-Dist: python-slugify>=8.0.0
Requires-Dist: obspy ; extra == "base"
Requires-Dist: openpyxl ; extra == "base"
Requires-Dist: pandas ; extra == "base"
Requires-Dist: numpy ; extra == "base"
Requires-Dist: matplotlib ; extra == "base"
Requires-Dist: magma-converter ; extra == "base"
Requires-Dist: peewee ; extra == "base"
Requires-Dist: python-slugify ; extra == "base"
Project-URL: Homepage, https://github.com/martanto/dsar
Project-URL: Issues, https://github.com/martanto/dsar/issues
Provides-Extra: base
